pyrnalist/__init__.py
pyrnalist/pyrnalist.py
pyrnalist-0.1.2.dist-info/LICENSE
pyrnalist-0.1.2.dist-info/METADATA
pyrnalist-0.1.2.dist-info/WHEEL
pyrnalist-0.1.2.dist-info/top_level.txt
pyrnalist-0.1.2.dist-info/RECORD
