Metadata-Version: 2.1
Name: pyrnalist
Version: 0.1.2
Summary: An elegant console reporter, a python port of Yournalist
Home-page: https://github.com/unjello/pyrnalist
Author: Andrzej Lichnerowicz
Author-email: andrzej@lichnerowicz.pl
Project-URL: Bug Tracker, https://github.com/unjello/pyrnalist/issues
Classifier: Programming Language :: Python :: 3
Classifier: License :: CC0 1.0 Universal (CC0 1.0) Public Domain Dedication
Classifier: Operating System :: OS Independent
Requires-Python: >=3.6
License-File: LICENSE
Requires-Dist: colorama (>=0.4)
Requires-Dist: psutil (>=5.8)
